{
  "version": "2.0",
  "logging": {
    "applicationInsights": {
      "samplingSettings": {
        "isEnabled": true,
        "excludedTypes": "Request"
      }
    },
    "logLevel": {
      "Default": "Information",
      "Microsoft.Azure.Functions.Worker": "Warning",
      "Function.ScheduleAppointment": "Debug"
    }  },  "extensions": {
    "http": {
      "routePrefix": "api",
      "enableHttps": false,      "cors": {
        "allowedOrigins": [
          "http://localhost:3000",
          "http://localhost:4200",
          "http://127.0.0.1:3000",
          "http://127.0.0.1:4200"
        ],
        "supportCredentials": false
      }
    }
  },
  "functionTimeout": "00:10:00"
}